langfree/__init__.py
langfree/_modidx.py
langfree/chatrecord.py
langfree/runs.py
langfree/shiny.py
langfree/transform.py
langfree-0.0.32.dist-info/LICENSE
langfree-0.0.32.dist-info/METADATA
langfree-0.0.32.dist-info/WHEEL
langfree-0.0.32.dist-info/entry_points.txt
langfree-0.0.32.dist-info/top_level.txt
langfree-0.0.32.dist-info/RECORD
