Metadata-Version: 2.1
Name: langfree
Version: 0.0.32
Summary: Utilities to help you work with your language model data outside LangSmith
Home-page: https://github.com/parlance-labs/langfree
Author: Hamel Husain
Author-email: hamel.husain@gmail.com
License: Apache Software License 2.0
Keywords: nbdev jupyter notebook python langchain langsmith openai
Classifier: Development Status :: 4 - Beta
Classifier: Intended Audience :: Developers
Classifier: Natural Language :: English
Classifier: Programming Language :: Python :: 3.7
Classifier: Programming Language :: Python :: 3.8
Classifier: Programming Language :: Python :: 3.9
Classifier: Programming Language :: Python :: 3.10
Classifier: License :: OSI Approved :: Apache Software License
Requires-Python: >=3.7
License-File: LICENSE
Requires-Dist: fastcore
Requires-Dist: pandas
Requires-Dist: tabulate
Requires-Dist: langchain >=0.1.9
Requires-Dist: langsmith >=0.1.9
Requires-Dist: pydantic
Requires-Dist: openai >=1.6.1
Requires-Dist: shiny >=0.6.1.1
Requires-Dist: langchain-core >=0.1.27
Provides-Extra: dev
